{ "SolutionInfo": { "Status": 2, "Runtime": 3.2200002670288086e-01, "Work": 4.3228194404659026e-02, "ObjVal": 925, "ObjBound": 925, "ObjBoundC": 925, "MIPGap": 0, "IntVio": 0, "BoundVio": 0, "ConstrVio": 0, "IterCount": 3768, "BarIterCount": 0, "NodeCount": 1731, "SolCount": 10, "PoolObjBound": 925, "PoolObjVal": [ 925, 933, 942, 943, 944, 1047, 1069, 1116, 1250, 1567]}, "Vars": [ { "VarName": "y[0,0,3]", "X": 1}, { "VarName": "y[0,1,1]", "X": 1}, { "VarName": "y[0,2,0]", "X": 1}, { "VarName": "y[1,0,2]", "X": 1}, { "VarName": "y[1,1,3]", "X": 1}, { "VarName": "y[1,2,2]", "X": 1}, { "VarName": "y[2,0,2]", "X": 1}, { "VarName": "y[2,1,1]", "X": 1}, { "VarName": "y[2,2,0]", "X": 1}, { "VarName": "x[0,0,0,1]", "X": 1}, { "VarName": "x[0,1,0,0]", "X": 1}, { "VarName": "x[0,1,1,0]", "X": 1}, { "VarName": "x[0,1,2,0]", "X": 1}, { "VarName": "x[0,1,2,2]", "X": 1}, { "VarName": "x[1,0,1,1]", "X": 1}, { "VarName": "x[1,0,1,2]", "X": 1}, { "VarName": "x[1,0,2,0]", "X": 1}, { "VarName": "x[1,1,2,1]", "X": 1}, { "VarName": "x[1,1,2,2]", "X": 1}, { "VarName": "x[1,2,2,2]", "X": 1}, { "VarName": "x[2,1,2,2]", "X": 1}, { "VarName": "s[0,0,3]", "X": 527}, { "VarName": "s[0,1,1]", "X": 497}, { "VarName": "s[0,2,0]", "X": 480}, { "VarName": "s[1,0,2]", "X": 832}, { "VarName": "s[1,1,3]", "X": 777}, { "VarName": "s[1,2,2]", "X": 480}, { "VarName": "s[2,0,2]", "X": 691}, { "VarName": "s[2,1,1]", "X": 621}, { "VarName": "s[2,2,0]", "X": 565}, { "VarName": "Z_FO", "X": 925}, { "VarName": "C119", "X": 1}, { "VarName": "C120", "X": 1}, { "VarName": "C122", "X": 1}]}