{ "SolutionInfo": { "Status": 9, "Runtime": 3.6012530000209808e+03, "Work": 4.0864672165827818e+02, "ObjVal": 298804925, "ObjBound": 2.6462454647434372e+08, "ObjBoundC": 2.6462454647434372e+08, "MIPGap": 1.1439027829161880e-01, "IntVio": 0, "BoundVio": 0, "ConstrVio": 1.7881393432617188e-07, "IterCount": 20719208, "BarIterCount": 0, "NodeCount": 3283431, "SolCount": 10, "PoolObjBound": 2.6462454647434372e+08, "PoolObjVal": [ 298804925, 299137749, 299164742, 299164743, 299164745, 299164747, 299164749, 299164751, 299164753, 299232111]}, "Vars": [ { "VarName": "y[0,0,10]", "X": 1}, { "VarName": "y[1,0,10]", "X": 1}, { "VarName": "y[2,0,21]", "X": 1}, { "VarName": "y[3,0,27]", "X": 1}, { "VarName": "y[4,0,27]", "X": 1}, { "VarName": "y[5,0,4]", "X": 1}, { "VarName": "y[6,0,3]", "X": 1}, { "VarName": "y[7,0,15]", "X": 1}, { "VarName": "y[8,0,0]", "X": 1}, { "VarName": "y[9,0,1]", "X": 1}, { "VarName": "y[10,0,8]", "X": 1}, { "VarName": "y[11,0,9]", "X": 1}, { "VarName": "y[12,0,5]", "X": 1}, { "VarName": "y[13,0,8]", "X": 1}, { "VarName": "y[14,0,0]", "X": 1}, { "VarName": "y[15,0,0]", "X": 1}, { "VarName": "y[16,0,9]", "X": 1}, { "VarName": "y[17,0,9]", "X": 1}, { "VarName": "y[18,0,12]", "X": 1}, { "VarName": "y[19,0,14]", "X": 1}, { "VarName": "y[20,0,16]", "X": 1}, { "VarName": "y[21,0,4]", "X": 1}, { "VarName": "y[22,0,3]", "X": 1}, { "VarName": "y[23,0,0]", "X": 1}, { "VarName": "y[24,0,22]", "X": 1}, { "VarName": "y[25,0,16]", "X": 1}, { "VarName": "y[26,0,16]", "X": 1}, { "VarName": "y[27,0,18]", "X": 1}, { "VarName": "y[28,0,18]", "X": 1}, { "VarName": "y[29,0,7]", "X": 1}, { "VarName": "y[30,0,20]", "X": 1}, { "VarName": "y[31,0,6]", "X": 1}, { "VarName": "y[32,0,25]", "X": 1}, { "VarName": "y[33,0,25]", "X": 1}, { "VarName": "y[34,0,6]", "X": 1}, { "VarName": "y[35,0,11]", "X": 1}, { "VarName": "y[36,0,28]", "X": 1}, { "VarName": "y[37,0,20]", "X": 1}, { "VarName": "y[38,0,23]", "X": 1}, { "VarName": "y[39,0,9]", "X": 1}, { "VarName": "y[40,0,2]", "X": 1}, { "VarName": "y[41,0,3]", "X": 1}, { "VarName": "y[42,0,13]", "X": 1}, { "VarName": "y[43,0,19]", "X": 1}, { "VarName": "y[44,0,30]", "X": 1}, { "VarName": "y[45,0,34]", "X": 1}, { "VarName": "y[46,0,6]", "X": 1}, { "VarName": "y[47,0,18]", "X": 1}, { "VarName": "y[48,0,18]", "X": 1}, { "VarName": "y[49,0,1]", "X": 1}, { "VarName": "y[50,0,7]", "X": 1}, { "VarName": "y[51,0,19]", "X": 1}, { "VarName": "y[52,0,12]", "X": 1}, { "VarName": "y[53,0,14]", "X": 1}, { "VarName": "y[54,0,17]", "X": 1}, { "VarName": "y[55,0,15]", "X": 1}, { "VarName": "y[55,1,11]", "X": 1}, { "VarName": "y[55,2,0]", "X": 1}, { "VarName": "y[55,3,0]", "X": 1}, { "VarName": "y[56,0,26]", "X": 1}, { "VarName": "y[57,0,20]", "X": 1}, { "VarName": "y[58,0,33]", "X": 1}, { "VarName": "y[59,0,32]", "X": 1}, { "VarName": "y[60,0,31]", "X": 1}, { "VarName": "y[61,0,11]", "X": 1}, { "VarName": "y[62,0,10]", "X": 1}, { "VarName": "y[63,0,10]", "X": 1}, { "VarName": "y[64,0,12]", "X": 1}, { "VarName": "y[65,0,22]", "X": 1}, { "VarName": "y[65,1,2]", "X": 1}, { "VarName": "y[65,2,5]", "X": 1}, { "VarName": "y[65,3,4]", "X": 1}, { "VarName": "y[66,0,13]", "X": 1}, { "VarName": "y[66,1,8]", "X": 1}, { "VarName": "y[66,2,3]", "X": 1}, { "VarName": "y[66,3,2]", "X": 1}, { "VarName": "y[67,0,15]", "X": 1}, { "VarName": "y[67,1,3]", "X": 1}, { "VarName": "y[67,2,5]", "X": 1}, { "VarName": "y[67,3,4]", "X": 1}, { "VarName": "y[68,0,27]", "X": 1}, { "VarName": "x[0,0,29,0]", "X": 1}, { "VarName": "x[0,0,34,0]", "X": 1}, { "VarName": "x[0,0,65,3]", "X": 1}, { "VarName": "x[0,0,66,3]", "X": 1}, { "VarName": "x[0,0,67,3]", "X": 1}, { "VarName": "x[1,0,10,0]", "X": 1}, { "VarName": "x[1,0,12,0]", "X": 1}, { "VarName": "x[1,0,13,0]", "X": 1}, { "VarName": "x[1,0,31,0]", "X": 1}, { "VarName": "x[1,0,40,0]", "X": 1}, { "VarName": "x[1,0,41,0]", "X": 1}, { "VarName": "x[1,0,46,0]", "X": 1}, { "VarName": "x[1,0,50,0]", "X": 1}, { "VarName": "x[1,0,63,0]", "X": 1}, { "VarName": "x[1,0,65,1]", "X": 1}, { "VarName": "x[1,0,65,3]", "X": 1}, { "VarName": "x[1,0,66,3]", "X": 1}, { "VarName": "x[1,0,67,1]", "X": 1}, { "VarName": "x[1,0,67,3]", "X": 1}, { "VarName": "x[3,0,56,0]", "X": 1}, { "VarName": "x[3,0,59,0]", "X": 1}, { "VarName": "x[3,0,68,0]", "X": 1}, { "VarName": "x[4,0,7,0]", "X": 1}, { "VarName": "x[4,0,51,0]", "X": 1}, { "VarName": "x[4,0,56,0]", "X": 1}, { "VarName": "x[4,0,59,0]", "X": 1}, { "VarName": "x[4,0,68,0]", "X": 1}, { "VarName": "x[5,0,13,0]", "X": 1}, { "VarName": "x[5,0,21,0]", "X": 1}, { "VarName": "x[5,0,22,0]", "X": 1}, { "VarName": "x[5,0,41,0]", "X": 1}, { "VarName": "x[5,0,65,1]", "X": 1}, { "VarName": "x[5,0,65,2]", "X": 1}, { "VarName": "x[5,0,65,3]", "X": 1}, { "VarName": "x[5,0,66,3]", "X": 1}, { "VarName": "x[5,0,67,1]", "X": 1}, { "VarName": "x[5,0,67,3]", "X": 1}, { "VarName": "x[6,0,9,0]", "X": 1}, { "VarName": "x[6,0,13,0]", "X": 1}, { "VarName": "x[6,0,21,0]", "X": 1}, { "VarName": "x[6,0,65,3]", "X": 1}, { "VarName": "x[6,0,66,1]", "X": 1}, { "VarName": "x[6,0,66,3]", "X": 1}, { "VarName": "x[6,0,67,1]", "X": 1}, { "VarName": "x[6,0,67,3]", "X": 1}, { "VarName": "x[7,0,35,0]", "X": 1}, { "VarName": "x[7,0,56,0]", "X": 1}, { "VarName": "x[7,0,59,0]", "X": 1}, { "VarName": "x[7,0,64,0]", "X": 1}, { "VarName": "x[7,0,67,0]", "X": 1}, { "VarName": "x[8,0,14,0]", "X": 1}, { "VarName": "x[9,0,49,0]", "X": 1}, { "VarName": "x[9,0,65,1]", "X": 1}, { "VarName": "x[9,0,66,1]", "X": 1}, { "VarName": "x[9,0,66,2]", "X": 1}, { "VarName": "x[9,0,66,3]", "X": 1}, { "VarName": "x[9,0,67,1]", "X": 1}, { "VarName": "x[10,0,12,0]", "X": 1}, { "VarName": "x[10,0,17,0]", "X": 1}, { "VarName": "x[10,0,29,0]", "X": 1}, { "VarName": "x[10,0,40,0]", "X": 1}, { "VarName": "x[10,0,41,0]", "X": 1}, { "VarName": "x[10,0,46,0]", "X": 1}, { "VarName": "x[10,0,50,0]", "X": 1}, { "VarName": "x[10,0,65,1]", "X": 1}, { "VarName": "x[10,0,65,2]", "X": 1}, { "VarName": "x[10,0,65,3]", "X": 1}, { "VarName": "x[10,0,66,3]", "X": 1}, { "VarName": "x[11,0,16,0]", "X": 1}, { "VarName": "x[11,0,17,0]", "X": 1}, { "VarName": "x[11,0,34,0]", "X": 1}, { "VarName": "x[11,0,39,0]", "X": 1}, { "VarName": "x[11,0,41,0]", "X": 1}, { "VarName": "x[11,0,46,0]", "X": 1}, { "VarName": "x[11,0,62,0]", "X": 1}, { "VarName": "x[11,0,63,0]", "X": 1}, { "VarName": "x[11,0,65,2]", "X": 1}, { "VarName": "x[11,0,65,3]", "X": 1}, { "VarName": "x[11,0,66,2]", "X": 1}, { "VarName": "x[11,0,66,3]", "X": 1}, { "VarName": "x[11,0,67,2]", "X": 1}, { "VarName": "x[11,0,67,3]", "X": 1}, { "VarName": "x[12,0,34,0]", "X": 1}, { "VarName": "x[12,0,40,0]", "X": 1}, { "VarName": "x[12,0,46,0]", "X": 1}, { "VarName": "x[12,0,49,0]", "X": 1}, { "VarName": "x[12,0,50,0]", "X": 1}, { "VarName": "x[12,0,66,1]", "X": 1}, { "VarName": "x[12,0,66,2]", "X": 1}, { "VarName": "x[12,0,67,1]", "X": 1}, { "VarName": "x[12,0,67,2]", "X": 1}, { "VarName": "x[13,0,21,0]", "X": 1}, { "VarName": "x[13,0,22,0]", "X": 1}, { "VarName": "x[13,0,29,0]", "X": 1}, { "VarName": "x[13,0,31,0]", "X": 1}, { "VarName": "x[13,0,34,0]", "X": 1}, { "VarName": "x[13,0,40,0]", "X": 1}, { "VarName": "x[13,0,41,0]", "X": 1}, { "VarName": "x[13,0,67,1]", "X": 1}, { "VarName": "x[13,0,67,3]", "X": 1}, { "VarName": "x[15,0,23,0]", "X": 1}, { "VarName": "x[15,0,55,2]", "X": 1}, { "VarName": "x[15,0,55,3]", "X": 1}, { "VarName": "x[16,0,17,0]", "X": 1}, { "VarName": "x[16,0,34,0]", "X": 1}, { "VarName": "x[16,0,39,0]", "X": 1}, { "VarName": "x[16,0,41,0]", "X": 1}, { "VarName": "x[16,0,46,0]", "X": 1}, { "VarName": "x[16,0,62,0]", "X": 1}, { "VarName": "x[16,0,63,0]", "X": 1}, { "VarName": "x[16,0,65,2]", "X": 1}, { "VarName": "x[16,0,65,3]", "X": 1}, { "VarName": "x[16,0,66,2]", "X": 1}, { "VarName": "x[16,0,66,3]", "X": 1}, { "VarName": "x[16,0,67,2]", "X": 1}, { "VarName": "x[16,0,67,3]", "X": 1}, { "VarName": "x[17,0,34,0]", "X": 1}, { "VarName": "x[17,0,39,0]", "X": 1}, { "VarName": "x[17,0,46,0]", "X": 1}, { "VarName": "x[17,0,62,0]", "X": 1}, { "VarName": "x[17,0,65,3]", "X": 1}, { "VarName": "x[17,0,66,2]", "X": 1}, { "VarName": "x[17,0,66,3]", "X": 1}, { "VarName": "x[17,0,67,3]", "X": 1}, { "VarName": "x[18,0,19,0]", "X": 1}, { "VarName": "x[18,0,24,0]", "X": 1}, { "VarName": "x[18,0,35,0]", "X": 1}, { "VarName": "x[18,0,51,0]", "X": 1}, { "VarName": "x[18,0,64,0]", "X": 1}, { "VarName": "x[19,0,64,0]", "X": 1}, { "VarName": "x[21,0,67,3]", "X": 1}, { "VarName": "x[22,0,65,1]", "X": 1}, { "VarName": "x[22,0,67,1]", "X": 1}, { "VarName": "x[22,0,67,2]", "X": 1}, { "VarName": "x[23,0,55,1]", "X": 1}, { "VarName": "x[24,0,43,0]", "X": 1}, { "VarName": "x[24,0,55,1]", "X": 1}, { "VarName": "x[24,0,57,0]", "X": 1}, { "VarName": "x[24,0,66,0]", "X": 1}, { "VarName": "x[24,0,67,0]", "X": 1}, { "VarName": "x[25,0,26,0]", "X": 1}, { "VarName": "x[28,0,55,1]", "X": 1}, { "VarName": "x[29,0,31,0]", "X": 1}, { "VarName": "x[29,0,34,0]", "X": 1}, { "VarName": "x[29,0,40,0]", "X": 1}, { "VarName": "x[29,0,41,0]", "X": 1}, { "VarName": "x[29,0,62,0]", "X": 1}, { "VarName": "x[30,0,35,0]", "X": 1}, { "VarName": "x[30,0,37,0]", "X": 1}, { "VarName": "x[30,0,51,0]", "X": 1}, { "VarName": "x[30,0,57,0]", "X": 1}, { "VarName": "x[31,0,34,0]", "X": 1}, { "VarName": "x[31,0,40,0]", "X": 1}, { "VarName": "x[31,0,41,0]", "X": 1}, { "VarName": "x[31,0,67,1]", "X": 1}, { "VarName": "x[32,0,36,0]", "X": 1}, { "VarName": "x[32,0,56,0]", "X": 1}, { "VarName": "x[33,0,36,0]", "X": 1}, { "VarName": "x[33,0,56,0]", "X": 1}, { "VarName": "x[34,0,40,0]", "X": 1}, { "VarName": "x[34,0,49,0]", "X": 1}, { "VarName": "x[34,0,62,0]", "X": 1}, { "VarName": "x[34,0,63,0]", "X": 1}, { "VarName": "x[34,0,65,3]", "X": 1}, { "VarName": "x[34,0,66,1]", "X": 1}, { "VarName": "x[34,0,66,3]", "X": 1}, { "VarName": "x[34,0,67,1]", "X": 1}, { "VarName": "x[34,0,67,2]", "X": 1}, { "VarName": "x[34,0,67,3]", "X": 1}, { "VarName": "x[35,0,42,0]", "X": 1}, { "VarName": "x[35,0,51,0]", "X": 1}, { "VarName": "x[35,0,53,0]", "X": 1}, { "VarName": "x[35,0,57,0]", "X": 1}, { "VarName": "x[35,0,61,0]", "X": 1}, { "VarName": "x[35,0,64,0]", "X": 1}, { "VarName": "x[36,0,56,0]", "X": 1}, { "VarName": "x[37,0,51,0]", "X": 1}, { "VarName": "x[37,0,57,0]", "X": 1}, { "VarName": "x[38,0,45,0]", "X": 1}, { "VarName": "x[38,0,58,0]", "X": 1}, { "VarName": "x[39,0,41,0]", "X": 1}, { "VarName": "x[39,0,46,0]", "X": 1}, { "VarName": "x[39,0,65,2]", "X": 1}, { "VarName": "x[39,0,66,2]", "X": 1}, { "VarName": "x[39,0,67,2]", "X": 1}, { "VarName": "x[39,0,67,3]", "X": 1}, { "VarName": "x[40,0,41,0]", "X": 1}, { "VarName": "x[40,0,46,0]", "X": 1}, { "VarName": "x[40,0,50,0]", "X": 1}, { "VarName": "x[40,0,65,3]", "X": 1}, { "VarName": "x[40,0,66,1]", "X": 1}, { "VarName": "x[40,0,67,1]", "X": 1}, { "VarName": "x[40,0,67,3]", "X": 1}, { "VarName": "x[41,0,62,0]", "X": 1}, { "VarName": "x[41,0,65,2]", "X": 1}, { "VarName": "x[41,0,66,1]", "X": 1}, { "VarName": "x[41,0,67,1]", "X": 1}, { "VarName": "x[41,0,67,3]", "X": 1}, { "VarName": "x[42,0,51,0]", "X": 1}, { "VarName": "x[42,0,55,1]", "X": 1}, { "VarName": "x[44,0,45,0]", "X": 1}, { "VarName": "x[45,0,58,0]", "X": 1}, { "VarName": "x[46,0,62,0]", "X": 1}, { "VarName": "x[46,0,65,1]", "X": 1}, { "VarName": "x[46,0,65,2]", "X": 1}, { "VarName": "x[46,0,67,1]", "X": 1}, { "VarName": "x[46,0,67,2]", "X": 1}, { "VarName": "x[47,0,48,0]", "X": 1}, { "VarName": "x[49,0,65,3]", "X": 1}, { "VarName": "x[49,0,67,2]", "X": 1}, { "VarName": "x[49,0,67,3]", "X": 1}, { "VarName": "x[50,0,65,1]", "X": 1}, { "VarName": "x[51,0,54,0]", "X": 1}, { "VarName": "x[51,0,55,1]", "X": 1}, { "VarName": "x[51,0,56,0]", "X": 1}, { "VarName": "x[51,0,57,0]", "X": 1}, { "VarName": "x[51,0,59,0]", "X": 1}, { "VarName": "x[51,0,61,0]", "X": 1}, { "VarName": "x[51,0,64,0]", "X": 1}, { "VarName": "x[51,0,65,0]", "X": 1}, { "VarName": "x[51,0,68,0]", "X": 1}, { "VarName": "x[52,0,64,0]", "X": 1}, { "VarName": "x[53,0,61,0]", "X": 1}, { "VarName": "x[55,0,56,0]", "X": 1}, { "VarName": "x[55,0,60,0]", "X": 1}, { "VarName": "x[55,0,61,0]", "X": 1}, { "VarName": "x[55,0,64,0]", "X": 1}, { "VarName": "x[55,0,65,0]", "X": 1}, { "VarName": "x[55,0,67,0]", "X": 1}, { "VarName": "x[55,0,68,0]", "X": 1}, { "VarName": "x[55,1,55,0]", "X": 1}, { "VarName": "x[55,1,55,2]", "X": 1}, { "VarName": "x[55,1,61,0]", "X": 1}, { "VarName": "x[55,1,64,0]", "X": 1}, { "VarName": "x[55,1,65,0]", "X": 1}, { "VarName": "x[55,1,67,0]", "X": 1}, { "VarName": "x[55,2,55,3]", "X": 1}, { "VarName": "x[55,3,55,1]", "X": 1}, { "VarName": "x[56,0,59,0]", "X": 1}, { "VarName": "x[56,0,68,0]", "X": 1}, { "VarName": "x[62,0,63,0]", "X": 1}, { "VarName": "x[62,0,65,3]", "X": 1}, { "VarName": "x[62,0,66,3]", "X": 1}, { "VarName": "x[63,0,65,3]", "X": 1}, { "VarName": "x[63,0,67,3]", "X": 1}, { "VarName": "x[64,0,67,0]", "X": 1}, { "VarName": "x[65,0,67,0]", "X": 1}, { "VarName": "x[65,1,65,3]", "X": 1}, { "VarName": "x[65,1,66,1]", "X": 1}, { "VarName": "x[65,1,67,1]", "X": 1}, { "VarName": "x[65,2,65,1]", "X": 1}, { "VarName": "x[65,2,65,3]", "X": 1}, { "VarName": "x[65,2,66,1]", "X": 1}, { "VarName": "x[65,2,66,2]", "X": 1}, { "VarName": "x[65,2,67,1]", "X": 1}, { "VarName": "x[65,2,67,2]", "X": 1}, { "VarName": "x[65,2,67,3]", "X": 1}, { "VarName": "x[65,3,65,2]", "X": 1}, { "VarName": "x[65,3,66,1]", "X": 1}, { "VarName": "x[65,3,66,3]", "X": 1}, { "VarName": "x[65,3,67,1]", "X": 1}, { "VarName": "x[65,3,67,2]", "X": 1}, { "VarName": "x[65,3,67,3]", "X": 1}, { "VarName": "x[66,1,66,3]", "X": 1}, { "VarName": "x[66,1,67,3]", "X": 1}, { "VarName": "x[66,2,66,1]", "X": 1}, { "VarName": "x[66,2,66,3]", "X": 1}, { "VarName": "x[66,2,67,1]", "X": 1}, { "VarName": "x[66,2,67,2]", "X": 1}, { "VarName": "x[66,2,67,3]", "X": 1}, { "VarName": "x[66,3,66,1]", "X": 1}, { "VarName": "x[66,3,66,2]", "X": 1}, { "VarName": "x[66,3,67,1]", "X": 1}, { "VarName": "x[66,3,67,2]", "X": 1}, { "VarName": "x[66,3,67,3]", "X": 1}, { "VarName": "x[67,2,67,1]", "X": 1}, { "VarName": "x[67,2,67,3]", "X": 1}, { "VarName": "x[67,3,67,1]", "X": 1}, { "VarName": "s[1,0,10]", "X": 1983871}, { "VarName": "s[3,0,27]", "X": 7.3009499999999988e+05}, { "VarName": "s[4,0,27]", "X": 2.5609650000000005e+06}, { "VarName": "s[5,0,4]", "X": 2929508}, { "VarName": "s[6,0,3]", "X": 600852}, { "VarName": "s[7,0,15]", "X": 1193884}, { "VarName": "s[8,0,0]", "X": 9.6828399999999988e+05}, { "VarName": "s[9,0,1]", "X": 1542386}, { "VarName": "s[11,0,9]", "X": 7.3914749999999553e+06}, { "VarName": "s[12,0,5]", "X": 369135}, { "VarName": "s[13,0,8]", "X": 1395870}, { "VarName": "s[15,0,0]", "X": 8.1353539999998212e+06}, { "VarName": "s[16,0,9]", "X": 4.4166379999999553e+06}, { "VarName": "s[17,0,9]", "X": 2226735}, { "VarName": "s[18,0,12]", "X": 1.1751859999999916e+06}, { "VarName": "s[20,0,16]", "X": 9.5258456047359374e-09}, { "VarName": "s[21,0,4]", "X": 4.5158599999999418e+05}, { "VarName": "s[22,0,3]", "X": 1386271}, { "VarName": "s[23,0,0]", "X": 1.5957679999999986e+06}, { "VarName": "s[25,0,16]", "X": 3850189}, { "VarName": "s[26,0,16]", "X": 1.7164349999999916e+06}, { "VarName": "s[27,0,18]", "X": 4.7999999999998192e+02}, { "VarName": "s[28,0,18]", "X": 1.6335859999999686e+06}, { "VarName": "s[30,0,20]", "X": 6588038}, { "VarName": "s[31,0,6]", "X": 1107968}, { "VarName": "s[33,0,25]", "X": 1162452}, { "VarName": "s[35,0,11]", "X": 1162103}, { "VarName": "s[37,0,20]", "X": 1.5211349999999993e+06}, { "VarName": "s[41,0,3]", "X": 2422141}, { "VarName": "s[42,0,13]", "X": 480}, { "VarName": "s[43,0,19]", "X": 480}, { "VarName": "s[46,0,6]", "X": 3204944}, { "VarName": "s[47,0,18]", "X": 5.4804559999999339e+06}, { "VarName": "s[48,0,18]", "X": 3.3109719999999553e+06}, { "VarName": "s[50,0,7]", "X": 3095426}, { "VarName": "s[51,0,19]", "X": 2164350}, { "VarName": "s[52,0,12]", "X": 2.6550559999999925e+06}, { "VarName": "s[53,0,14]", "X": 1.5290700000000002e+06}, { "VarName": "s[55,0,15]", "X": 8025419}, { "VarName": "s[55,1,11]", "X": 4137419}, { "VarName": "s[55,2,0]", "X": 5951819}, { "VarName": "s[55,3,0]", "X": 3470575}, { "VarName": "s[62,0,10]", "X": 3169006}, { "VarName": "s[63,0,10]", "X": 9.1896799999999860e+05}, { "VarName": "s[65,0,22]", "X": 3895328}, { "VarName": "s[65,1,2]", "X": 1176128}, { "VarName": "s[65,2,5]", "X": 2535728}, { "VarName": "s[65,3,4]", "X": 1.4874559999999925e+06}, { "VarName": "s[66,0,13]", "X": 7206012}, { "VarName": "s[66,1,8]", "X": 3442373}, { "VarName": "s[66,2,3]", "X": 3832025}, { "VarName": "s[66,3,2]", "X": 3922812}, { "VarName": "s[67,0,15]", "X": 518400}, { "VarName": "Z_FO", "X": 298804925}]}